src/__init__.py
src/api/server.py
src/client/__init__.py
src/client/cli.py
src/client/client.py
src/core/__init__.py
src/core/audit_blockchain_adapter.py
src/core/audit_plane.py
src/core/blockchain.py
src/core/capability.py
src/core/capability_store.py
src/core/crypto.py
src/core/did.py
src/core/gateway.py
src/core/key_security.py
src/core/light.py
src/core/message.py
src/core/rate_limiter.py
src/core/serialization.py
src/core/session.py
src/core/storage.py
src/core/sync.py
src/core/validation/__init__.py
src/core/validation/engine.py
src/core/validation/layers.py
src/core/validation/proofs.py
src/core/validation/report.py
src/engine/__init__.py
src/engine/chunker.py
src/engine/engine.py
src/engine/media.py
src/mcp_bridge/__init__.py
src/mcp_bridge/acl.py
src/mcp_bridge/proxy.py
src/network/__init__.py
src/network/dht.py
src/network/p2p.py
src/network/peer.py
src/network/pool.py
src/network/protocol.py
src/server/__init__.py
src/server/registry.py
src/server/server.py
talos/__init__.py
talos/capability.py
talos/channel.py
talos/client.py
talos/config.py
talos/exceptions.py
talos/identity.py
talos_protocol-3.3.9.dist-info/licenses/LICENSE
talos_protocol-3.3.9.dist-info/licenses/NOTICE
talos_protocol-3.3.9.dist-info/METADATA
talos_protocol-3.3.9.dist-info/WHEEL
talos_protocol-3.3.9.dist-info/entry_points.txt
talos_protocol-3.3.9.dist-info/top_level.txt
talos_protocol-3.3.9.dist-info/RECORD
