Metadata-Version: 2.4
Name: talos-protocol
Version: 3.3.9
Summary: Talos: A secure, decentralized protocol for AI Agent communication
Requires-Python: >=3.11
License-File: LICENSE
License-File: NOTICE
Requires-Dist: cryptography>=41.0.0
Requires-Dist: websockets>=12.0
Requires-Dist: click>=8.1.0
Requires-Dist: msgpack>=1.0.0
Requires-Dist: pydantic>=2.0.0
Requires-Dist: aiohttp>=3.9.0
Requires-Dist: pyyaml>=6.0.0
Requires-Dist: lmdb>=1.4.1
Requires-Dist: orjson>=3.9.0
Provides-Extra: dev
Requires-Dist: pytest>=7.4.0; extra == "dev"
Requires-Dist: pytest-asyncio>=0.21.0; extra == "dev"
Requires-Dist: pytest-cov>=4.1.0; extra == "dev"
Requires-Dist: ruff>=0.1.0; extra == "dev"
Requires-Dist: mypy>=1.7.0; extra == "dev"
Dynamic: license-file
